{
  "nodes": [
    {
      "name": "CatSelectContent",
      "children": [
        1,
        7,
        13,
        19
      ]
    },
    {
      "name": "Cell1",
      "children": [
        2,
        3,
        4,
        5,
        6
      ]
    },
    {
      "name": "NameText"
    },
    {
      "name": "IconImage"
    },
    {
      "name": "PhotoImage"
    },
    {
      "name": "DateText"
    },
    {
      "name": "NewImage"
    },
    {
      "name": "Cell2",
      "children": [
        8,
        9,
        10,
        11,
        12
      ]
    },
    {
      "name": "NameText"
    },
    {
      "name": "IconImage"
    },
    {
      "name": "PhotoImage"
    },
    {
      "name": "DateText"
    },
    {
      "name": "NewImage"
    },
    {
      "name": "Cell3",
      "children": [
        14,
        15,
        16,
        17,
        18
      ]
    },
    {
      "name": "NameText"
    },
    {
      "name": "IconImage"
    },
    {
      "name": "PhotoImage"
    },
    {
      "name": "DateText"
    },
    {
      "name": "NewImage"
    },
    {
      "name": "Cell4",
      "children": [
        20,
        21,
        22,
        23,
        24
      ]
    },
    {
      "name": "NameText"
    },
    {
      "name": "IconImage"
    },
    {
      "name": "PhotoImage"
    },
    {
      "name": "DateText"
    },
    {
      "name": "NewImage"
    }
  ],
  "scene": 0,
  "scenes": [
    {
      "nodes": [
        0
      ]
    }
  ]
}