{
  "nodes": [
    {
      "name": "SealDecoPage",
      "children": [
        1,
        4,
        7,
        10
      ]
    },
    {
      "name": "Cell0",
      "children": [
        2,
        3
      ]
    },
    {
      "name": "Text"
    },
    {
      "name": "Image"
    },
    {
      "name": "Cell1",
      "children": [
        5,
        6
      ]
    },
    {
      "name": "Text"
    },
    {
      "name": "Image"
    },
    {
      "name": "Cell2",
      "children": [
        8,
        9
      ]
    },
    {
      "name": "Text"
    },
    {
      "name": "Image"
    },
    {
      "name": "Cell3",
      "children": [
        11,
        12
      ]
    },
    {
      "name": "Text"
    },
    {
      "name": "Image"
    }
  ],
  "scene": 0,
  "scenes": [
    {
      "nodes": [
        0
      ]
    }
  ]
}